sequgen/__init__.py
sequgen/__version__.py
sequgen/dimension.py
sequgen/parameter_space.py
sequgen/deterministic/__init__.py
sequgen/deterministic/boxcar.py
sequgen/deterministic/constant.py
sequgen/deterministic/normal_peak.py
sequgen/deterministic/sine.py
sequgen/deterministic/triangular_peak.py
sequgen/samplers/__init__.py
sequgen/samplers/sample_uniform_random.py
sequgen/stochastic/__init__.py
sequgen/stochastic/gaussian.py
sequgen-0.2.0.data/data/citation/sequgen/CITATION.cff
sequgen-0.2.0.dist-info/LICENSE
sequgen-0.2.0.dist-info/METADATA
sequgen-0.2.0.dist-info/NOTICE
sequgen-0.2.0.dist-info/WHEEL
sequgen-0.2.0.dist-info/top_level.txt
sequgen-0.2.0.dist-info/RECORD
